rglogger.py
rglogger-1.6.0.dist-info/DESCRIPTION.rst
rglogger-1.6.0.dist-info/METADATA
rglogger-1.6.0.dist-info/RECORD
rglogger-1.6.0.dist-info/WHEEL
rglogger-1.6.0.dist-info/metadata.json
rglogger-1.6.0.dist-info/top_level.txt
