Metadata-Version: 2.0
Name: rglogger
Version: 1.6.0
Summary: Use Python's standard logging library to send messages to Raygun (https://raygun.io/)
Home-page: https://github.com/mirusresearch/raygun-logger
Author: Don Spaulding
Author-email: don@mirusresearch.com
License: MIT
Keywords: raygun logging exceptions
Platform: UNKNOWN
Classifier: Development Status :: 4 - Beta
Classifier: Intended Audience :: Developers
Classifier: License :: OSI Approved :: MIT License
Classifier: Programming Language :: Python :: 2
Classifier: Programming Language :: Python :: 2.7
Classifier: Programming Language :: Python :: 3
Classifier: Programming Language :: Python :: 3.4
Classifier: Programming Language :: Python :: 3.5
Requires-Dist: jsonpickle
Requires-Dist: requests
Requires-Dist: six
